{
    "preguntas": {
        "P0": "¿Cuántos lados tiene la figura?",
        "P1": "¿Tiene radio constante (perfectamente redonda)?",
        "P3": "¿Tiene todos sus lados iguales?",
        "P3_1": "¿Tiene al menos dos lados iguales?",
        "P3_2": "¿Tiene un angulo recto (90°)",
        "P4": "¿Tiene todos sus lados iguales?",
        "P4_1": "¿Tiene todos sus ángulos iguales (90°)?",
        "P4_2": "¿Tiene al menos un par de lados paralelos?",
        "P4_3": "¿Tiene dos pares de lados paralelos?",
        "P4_4": "¿Tiene todos sus ángulos iguales (90°)?",
        "P10": "¿La figura tiene puntas hacia adentro (cóncava)?",
        "P12": "¿La figura tiene puntas hacia adentro (cóncava)?"
    },
    "grafo": {
        "P0": {
            "0": "P1",
            "3": "P3",
            "4": "P4",
            "5": "Pentágono",
            "6": "Hexágono",
            "7": "Heptágono",
            "8": "Octágono",
            "9": "Eneágono",
            "10": "P10",
            "11": "Endecágono",
            "12": "P12"
        },
        "P1": {
            "S": "Círculo",
            "N": "Elipse"
        },
        "P3": {
            "S": "Triángulo Equilátero",
            "N": "P3_1"
        },
        "P3_1": {
            "S": "Triángulo Isósceles",
            "N": "P3_2"
        },
        "P3_2":{
            "S": "Triángulo Rectangulo",
            "N": "Triángulo Escaleno"
        },
        "P4": {
            "S": "P4_1",
            "N": "P4_2"
        },
        "P4_1": {
            "S": "Cuadrado",
            "N": "Rombo"
        },
        "P4_2": {
            "S": "P4_3",
            "N": "Trapezoide"
        },
        "P4_3": {
            "S": "P4_4",
            "N": "Trapecio"
        },
        "P4_4": {
            "S": "Rectángulo",
            "N": "Romboide"
        },
        "P10": {
            "S": "Pentagrama (Estrella de 5 puntas)",
            "N": "Decágono"
        },
        "P12": {
            "S": "Hexagrama (Estrella de 6 puntas)",
            "N": "Dodecágono"
        }
    }
}